terminalplotter.py
terminalplotter-0.0.3.dist-info/METADATA
terminalplotter-0.0.3.dist-info/WHEEL
terminalplotter-0.0.3.dist-info/top_level.txt
terminalplotter-0.0.3.dist-info/RECORD
